ocrd_page_to_alto/__init__.py
ocrd_page_to_alto/cli.py
ocrd_page_to_alto/convert.py
ocrd_page_to_alto/ocrd-tool.json
ocrd_page_to_alto/ocrd_cli.py
ocrd_page_to_alto/ocrd_processor.py
ocrd_page_to_alto/styles.py
ocrd_page_to_alto/utils.py
ocrd_page_to_alto-2.1.0.dist-info/licenses/LICENSE
ocrd_page_to_alto-2.1.0.dist-info/METADATA
ocrd_page_to_alto-2.1.0.dist-info/WHEEL
ocrd_page_to_alto-2.1.0.dist-info/entry_points.txt
ocrd_page_to_alto-2.1.0.dist-info/top_level.txt
ocrd_page_to_alto-2.1.0.dist-info/RECORD
