Metadata-Version: 2.4
Name: ocrd-page-to-alto
Version: 2.1.0
Summary: Convert PAGE (v. 2019) to ALTO (v. 2.0 - 4.2)
Author-email: Konstantin Baierer <unixprog@gmail.com>
License: Apache License 2.0
Project-URL: Homepage, https://github.com/OCR-D/page-to-alto
Project-URL: Repository, https://github.com/OCR-D/page-to-alto
Requires-Python: >=3.7
License-File: LICENSE
Requires-Dist: ocrd>=3.3.1
Requires-Dist: lxml
Requires-Dist: langcodes<3.5.0,>=3.4.0; python_version > "3.7"
Requires-Dist: langcodes[data]<3.5.0,>=3.1.0; python_version <= "3.7"
Requires-Dist: language_data<1.3.0; python_version < "3.9"
Requires-Dist: packaging
Dynamic: license-file
